{
  "dias": [
    {
      "data": "2026-07-15",
      "ultima_atualizacao": "2026-07-15T20:14:51-03:00",
      "finalizados": 1,
      "taxa_geral": 0.75,
      "total_acertos": 3,
      "total_palpites": 4,
      "mercados": {
        "WINNER": {
          "acertos": 0,
          "total": 1,
          "taxa": 0.0
        },
        "OVER_UNDER": {
          "acertos": 2,
          "total": 2,
          "taxa": 1.0
        },
        "BTTS": {
          "acertos": 1,
          "total": 1,
          "taxa": 1.0
        }
      },
      "metricas_probabilisticas": {
        "1X2": {
          "n": 1,
          "brier": 0.6286,
          "log_loss": 1.0294
        },
        "OVER_UNDER": {
          "n": 1,
          "brier": 0.1252,
          "log_loss": 0.4367
        },
        "BTTS": {
          "n": 1,
          "brier": 0.109,
          "log_loss": 0.4007
        }
      },
      "jogos": [
        {
          "data_jogo": "2026-07-15T19:00:00Z",
          "casa": "England",
          "visitante": "Argentina",
          "competicao": "FIFA World Cup",
          "placar": "1-2",
          "palpites": [
            {
              "tipo": "WINNER",
              "opcao": "1",
              "confianca": "LOW",
              "probabilidade": 0.388,
              "resultado": "ERRO"
            },
            {
              "tipo": "OVER_UNDER",
              "opcao": "UNDER_3.5",
              "confianca": "LOW",
              "probabilidade": 0.574,
              "resultado": "ACERTO"
            },
            {
              "tipo": "OVER_UNDER",
              "opcao": "OVER_1.5",
              "confianca": "HIGH",
              "probabilidade": 0.915,
              "resultado": "ACERTO"
            },
            {
              "tipo": "BTTS",
              "opcao": "YES",
              "confianca": "HIGH",
              "probabilidade": 0.735,
              "resultado": "ACERTO"
            }
          ]
        }
      ]
    },
    {
      "data": "2026-07-14",
      "ultima_atualizacao": "2026-07-14T23:07:34-03:00",
      "finalizados": 1,
      "taxa_geral": 0.75,
      "total_acertos": 3,
      "total_palpites": 4,
      "mercados": {
        "WINNER": {
          "acertos": 0,
          "total": 1,
          "taxa": 0.0
        },
        "OVER_UNDER": {
          "acertos": 2,
          "total": 2,
          "taxa": 1.0
        },
        "BTTS": {
          "acertos": 1,
          "total": 1,
          "taxa": 1.0
        }
      },
      "metricas_probabilisticas": {
        "1X2": {
          "n": 1,
          "brier": 1.0382,
          "log_loss": 1.6983
        },
        "OVER_UNDER": {
          "n": 1,
          "brier": 0.2204,
          "log_loss": 0.6338
        },
        "BTTS": {
          "n": 1,
          "brier": 0.241,
          "log_loss": 0.6752
        }
      },
      "jogos": [
        {
          "data_jogo": "2026-07-14T19:00:00Z",
          "casa": "France",
          "visitante": "Spain",
          "competicao": "FIFA World Cup",
          "placar": "0-2",
          "palpites": [
            {
              "tipo": "WINNER",
              "opcao": "1",
              "confianca": "MEDIUM",
              "probabilidade": 0.544,
              "resultado": "ERRO"
            },
            {
              "tipo": "OVER_UNDER",
              "opcao": "UNDER_2.5",
              "confianca": "LOW",
              "probabilidade": 0.531,
              "resultado": "ACERTO"
            },
            {
              "tipo": "OVER_UNDER",
              "opcao": "OVER_1.5",
              "confianca": "HIGH",
              "probabilidade": 0.858,
              "resultado": "ACERTO"
            },
            {
              "tipo": "BTTS",
              "opcao": "NO",
              "confianca": "LOW",
              "probabilidade": 0.372,
              "resultado": "ACERTO"
            }
          ]
        }
      ]
    },
    {
      "data": "2026-07-13",
      "ultima_atualizacao": "2026-07-13T23:16:07-03:00",
      "finalizados": 0,
      "taxa_geral": 0.0,
      "total_acertos": 0,
      "total_palpites": 0,
      "mercados": {},
      "metricas_probabilisticas": {
        "1X2": {
          "n": 0,
          "brier": null,
          "log_loss": null
        },
        "OVER_UNDER": {
          "n": 0,
          "brier": null,
          "log_loss": null
        },
        "BTTS": {
          "n": 0,
          "brier": null,
          "log_loss": null
        }
      },
      "jogos": []
    },
    {
      "data": "2026-07-12",
      "ultima_atualizacao": "2026-07-12T23:31:33-03:00",
      "finalizados": 1,
      "taxa_geral": 0.5,
      "total_acertos": 2,
      "total_palpites": 4,
      "mercados": {
        "WINNER": {
          "acertos": 1,
          "total": 1,
          "taxa": 1.0
        },
        "OVER_UNDER": {
          "acertos": 1,
          "total": 2,
          "taxa": 0.5
        },
        "BTTS": {
          "acertos": 0,
          "total": 1,
          "taxa": 0.0
        }
      },
      "metricas_probabilisticas": {
        "1X2": {
          "n": 1,
          "brier": 0.2731,
          "log_loss": 0.5556
        },
        "OVER_UNDER": {
          "n": 1,
          "brier": 0.1286,
          "log_loss": 0.444
        },
        "BTTS": {
          "n": 1,
          "brier": 0.1415,
          "log_loss": 0.472
        }
      },
      "jogos": [
        {
          "data_jogo": "2026-07-12T01:00:00Z",
          "casa": "Argentina",
          "visitante": "Switzerland",
          "competicao": "FIFA World Cup",
          "placar": "3-1",
          "palpites": [
            {
              "tipo": "WINNER",
              "opcao": "1",
              "confianca": "MEDIUM",
              "probabilidade": 0.574,
              "resultado": "ACERTO"
            },
            {
              "tipo": "OVER_UNDER",
              "opcao": "UNDER_3.5",
              "confianca": "LOW",
              "probabilidade": 0.58,
              "resultado": "ERRO"
            },
            {
              "tipo": "OVER_UNDER",
              "opcao": "OVER_1.5",
              "confianca": "HIGH",
              "probabilidade": 0.986,
              "resultado": "ACERTO"
            },
            {
              "tipo": "BTTS",
              "opcao": "NO",
              "confianca": "LOW",
              "probabilidade": 0.226,
              "resultado": "ERRO"
            }
          ]
        }
      ]
    },
    {
      "data": "2026-07-11",
      "ultima_atualizacao": "2026-07-11T23:39:57-03:00",
      "finalizados": 1,
      "taxa_geral": 0.75,
      "total_acertos": 3,
      "total_palpites": 4,
      "mercados": {
        "WINNER": {
          "acertos": 1,
          "total": 1,
          "taxa": 1.0
        },
        "OVER_UNDER": {
          "acertos": 1,
          "total": 2,
          "taxa": 0.5
        },
        "BTTS": {
          "acertos": 1,
          "total": 1,
          "taxa": 1.0
        }
      },
      "metricas_probabilisticas": {
        "1X2": {
          "n": 1,
          "brier": 0.3366,
          "log_loss": 0.6404
        },
        "OVER_UNDER": {
          "n": 1,
          "brier": 0.0523,
          "log_loss": 0.2598
        },
        "BTTS": {
          "n": 1,
          "brier": 0.0637,
          "log_loss": 0.2909
        }
      },
      "jogos": [
        {
          "data_jogo": "2026-07-11T21:00:00Z",
          "casa": "Norway",
          "visitante": "England",
          "competicao": "FIFA World Cup",
          "placar": "1-2",
          "palpites": [
            {
              "tipo": "WINNER",
              "opcao": "2",
              "confianca": "MEDIUM",
              "probabilidade": 0.527,
              "resultado": "ACERTO"
            },
            {
              "tipo": "OVER_UNDER",
              "opcao": "OVER_3.5",
              "confianca": "LOW",
              "probabilidade": 0.579,
              "resultado": "ERRO"
            },
            {
              "tipo": "OVER_UNDER",
              "opcao": "OVER_1.5",
              "confianca": "HIGH",
              "probabilidade": 0.94,
              "resultado": "ACERTO"
            },
            {
              "tipo": "BTTS",
              "opcao": "YES",
              "confianca": "HIGH",
              "probabilidade": 0.768,
              "resultado": "ACERTO"
            }
          ]
        }
      ]
    }
  ]
}